satellitic/__init__.py
satellitic/beam.py
satellitic/constants.py
satellitic/constellation.py
satellitic/convert.py
satellitic/init.py
satellitic/iotools.py
satellitic/power.py
satellitic/propagate.py
satellitic/simulation.py
satellitic/visualise.py
satellitic-0.1.15.dist-info/METADATA
satellitic-0.1.15.dist-info/WHEEL
satellitic-0.1.15.dist-info/licenses/LICENSE
satellitic-0.1.15.dist-info/RECORD
