Metadata-Version: 2.4
Name: satellitic
Version: 0.1.15
Summary: A collection of satellite methods and approaches to satellite simulations
Project-URL: Homepage, https://github.com/richardtjornhammar/satellitic
Project-URL: Issues, https://github.com/richardtjornhammar/satellitic
Author-email: Richard Tjörnhammar <richard.tjornhammar@gmail.com>
License-Expression: Apache-2.0
License-File: LICENSE
Classifier: License :: OSI Approved :: Apache Software License
Classifier: Operating System :: OS Independent
Classifier: Programming Language :: Python :: 3.13
Requires-Python: >=3.11
Requires-Dist: astropy>=5.1
Requires-Dist: jax>=0.4.10
Requires-Dist: matplotlib>=3.7
Requires-Dist: numpy>=1.23
Requires-Dist: pandas>=2.0.3
Requires-Dist: pyqt5>=5.15
Requires-Dist: requests>=2.31
Requires-Dist: sgp4>=2.21
Requires-Dist: vispy>=0.13
